FaceDec.py
FaceDetector_cc-0.0.2.dist-info/LICENSE
FaceDetector_cc-0.0.2.dist-info/METADATA
FaceDetector_cc-0.0.2.dist-info/WHEEL
FaceDetector_cc-0.0.2.dist-info/top_level.txt
FaceDetector_cc-0.0.2.dist-info/RECORD
