Metadata-Version: 2.1
Name: FaceDetector-cc
Version: 0.0.2
Summary: Simple python package to simply use mediapipe face detection.
Home-page: https://github.com/Chexa12cc/FaceDetector-cc
Download-URL: https://pypi.org/project/FaceDetector-cc/
Author: Chanchal Roy
Author-email: croy7667@gmail.com
Maintainer: Chanchal Roy
Maintainer-email: croy7667@gmail.com
License: MIT
Project-URL: Bug Tracker, https://github.com/Chexa12cc/FaceDetector-cc/issues
Keywords: Mediapipe,Opencv,Face Detection,Python
Classifier: Programming Language :: Python :: 3
Classifier: License :: OSI Approved :: MIT License
Classifier: Operating System :: OS Independent
Requires-Python: >=3.6
License-File: LICENSE
Requires-Dist: mediapipe
Requires-Dist: opencv-python
